zhis/__init__.py
zhis/__main__.py
zhis/__version__.py
zhis/cli/__init__.py
zhis/cli/commands/__init__.py
zhis/cli/commands/history.py
zhis/cli/commands/import_histfile.py
zhis/cli/commands/init.py
zhis/cli/commands/search.py
zhis/cli/options/__init__.py
zhis/cli/options/config.py
zhis/cli/options/filter.py
zhis/cli/options/verbose.py
zhis/config/__init__.py
zhis/config/config.py
zhis/db/__init__.py
zhis/db/models.py
zhis/db/setup.py
zhis/db/types.py
zhis/gui/__init__.py
zhis/gui/gui.py
zhis/gui/styles/main.tcss
zhis/gui/types.py
zhis/main.py
zhis/utils/__init__.py
zhis/utils/helpers.py
zhis-0.1.0.dist-info/LICENSE
zhis-0.1.0.dist-info/METADATA
zhis-0.1.0.dist-info/WHEEL
zhis-0.1.0.dist-info/entry_points.txt
zhis-0.1.0.dist-info/RECORD
