Metadata-Version: 2.1
Name: zhis
Version: 0.1.0
Summary: zhis: Command history with a database twist.
License: MIT
Author: Norbert Batiuk
Author-email: norbert@batiuk.se
Requires-Python: >=3.11,<4.0
Classifier: License :: OSI Approved :: MIT License
Classifier: Programming Language :: Python :: 3
Classifier: Programming Language :: Python :: 3.11
Classifier: Programming Language :: Python :: 3.12
Classifier: Programming Language :: Python :: 3.13
Requires-Dist: click (==8.1.8)
Requires-Dist: marshmallow-dataclass (==8.7.1)
Requires-Dist: peewee (==3.17.8)
Requires-Dist: pyyaml (>=6.0.2,<7.0.0)
Requires-Dist: textual (==1.0.0)
